think_llm_client/__init__.py
think_llm_client/client.py
think_llm_client/exceptions.py
think_llm_client/cli/__init__.py
think_llm_client/cli/client.py
think_llm_client/utils/__init__.py
think_llm_client/utils/config.py
think_llm_client/utils/display.py
think_llm_client/utils/logger.py
think_llm_client/utils/terminal_config.py
think_llm_client-0.4.1.dist-info/METADATA
think_llm_client-0.4.1.dist-info/WHEEL
think_llm_client-0.4.1.dist-info/RECORD
