Metadata-Version: 2.4
Name: think-llm-client
Version: 0.4.1
Summary: A flexible SDK for LLM and VLM model interactions with CLI support
Project-URL: Homepage, https://github.com/thinkthinking/think-llm-client
Project-URL: Documentation, https://github.com/thinkthinking/think-llm-client#readme
Project-URL: Repository, https://github.com/thinkthinking/think-llm-client.git
Project-URL: Issues, https://github.com/thinkthinking/think-llm-client/issues
Author-email: ThinkThinking <yezhenjie@outlook.de>
License: MIT
Keywords: ai,cli,gpt,llm,openai,vision
Classifier: Development Status :: 4 - Beta
Classifier: Environment :: Console
Classifier: Intended Audience :: Developers
Classifier: License :: OSI Approved :: MIT License
Classifier: Operating System :: OS Independent
Classifier: Programming Language :: Python :: 3.10
Classifier: Programming Language :: Python :: 3.11
Classifier: Topic :: Software Development :: Libraries :: Python Modules
Requires-Python: >=3.12
Requires-Dist: anthropic>=0.49.0
Requires-Dist: httpx[socks]
Requires-Dist: openai>=1.65.4
Requires-Dist: python-dotenv>=0.19.0
Requires-Dist: rich>=13.0.0
Provides-Extra: dev
Requires-Dist: black>=23.0; extra == 'dev'
Requires-Dist: mypy>=1.0; extra == 'dev'
Requires-Dist: pytest-asyncio>=0.23.0; extra == 'dev'
Requires-Dist: pytest-cov>=4.1.0; extra == 'dev'
Requires-Dist: pytest>=7.0; extra == 'dev'
Requires-Dist: ruff>=0.1.0; extra == 'dev'
